datasette_auth0/__init__.py
datasette_auth0-0.1.dist-info/LICENSE
datasette_auth0-0.1.dist-info/METADATA
datasette_auth0-0.1.dist-info/WHEEL
datasette_auth0-0.1.dist-info/entry_points.txt
datasette_auth0-0.1.dist-info/top_level.txt
datasette_auth0-0.1.dist-info/RECORD
