Metadata-Version: 2.1
Name: datasette-auth0
Version: 0.1
Summary: Datasette plugin that authenticates users using Auth0
Home-page: https://github.com/simonw/datasette-auth0
Author: Simon Willison
License: Apache License, Version 2.0
Project-URL: Issues, https://github.com/simonw/datasette-auth0/issues
Project-URL: CI, https://github.com/simonw/datasette-auth0/actions
Project-URL: Changelog, https://github.com/simonw/datasette-auth0/releases
Platform: UNKNOWN
Classifier: Framework :: Datasette
Classifier: License :: OSI Approved :: Apache Software License
Requires-Python: >=3.7
License-File: LICENSE
Requires-Dist: datasette
Provides-Extra: test
Requires-Dist: pytest ; extra == 'test'
Requires-Dist: pytest-asyncio ; extra == 'test'
Requires-Dist: pytest-httpx ; extra == 'test'
